flora_sensor/__init__.py
flora_sensor/flora_sensor.py
flutter/flora_sensor/pubspec.yaml
flutter/flora_sensor/lib/flora_sensor.dart
flutter/flora_sensor/lib/src/create_control.dart
flutter/flora_sensor/lib/src/flora_sensor.dart
flora_sensor-0.0.1.dist-info/METADATA
flora_sensor-0.0.1.dist-info/WHEEL
flora_sensor-0.0.1.dist-info/top_level.txt
flora_sensor-0.0.1.dist-info/RECORD
